sho/__init__.py
sho/constants.py
sho/sho.py
sho-0.4.24.dist-info/AUTHORS.rst
sho-0.4.24.dist-info/LICENSE
sho-0.4.24.dist-info/METADATA
sho-0.4.24.dist-info/WHEEL
sho-0.4.24.dist-info/top_level.txt
sho-0.4.24.dist-info/RECORD
